[{"pyment":"sell","userid":"24.0064,89.2372","email":"demo@demo.com","phone":"01725570745","method":"nagad","account":"01877357091","usdAmount":"322","bdtAmount":"34132","fee":"6.44 USD","rbdt":"33449.36BDT","tokenname":"bep20","address":"2","transaction":"hdsghsjhhdjhdbd"},{"pyment":"sell","userid":"24.0064,89.2372","email":"demo@demo.com","phone":"01725570745","method":"upay","account":"Sorry our Upay service is not launched.","usdAmount":"67","bdtAmount":"7102","fee":"1.34 USD","rbdt":"6959.96BDT","tokenname":"bep20","address":"2","transaction":"jrj"},{"pyment":"sell","userid":"24.0064,89.2372","email":"1@1.1","phone":"1","method":"nagad","account":"01877357091","usdAmount":"67","bdtAmount":"7102","fee":"1.34 USD","rbdt":"6959.96BDT","tokenname":"bep20","address":"2","transaction":"eferggtrdg"},{"pyment":"sell","userid":"24.0064,89.2372","email":"demo@demo.com","phone":"1234567890","method":"nagad","account":"01568834415","usdAmount":"67","bdtAmount":"7102","fee":"1.34 USD","rbdt":"6959.96BDT","tokenname":"bep20","address":"2","transaction":"eferggtrdg"},{"pyment":"sell","userid":"24.0064,89.2372","email":"demo@demo.com","phone":"1234567890","method":"nagad","account":"01568834415","usdAmount":"67","bdtAmount":"7102","fee":"1.34 USD","rbdt":"6959.96BDT","tokenname":"trc20","address":"3","transaction":"3","datetime":"2024-04-21 19:14:48"}]